Metadata-Version: 1.0
Name: fin-tools
Version: 0.1.7
Summary: common financial tools for risk and pricing
Home-page: https://github.com/laholmes/fin-tools
Author: laurence holmes
Author-email: laholmes@hotmail.co.uk
License: UNKNOWN
Platform: UNKNOWN
